hue_api/__init__.py
hue_api/exceptions.py
hue_api/groups.py
hue_api/hue.py
hue_api/lights.py
hue_api/scene.py
hue_api/state.py
tests/__init__.py
tests/test_hue.py
hue_py-0.3.1.dist-info/METADATA
hue_py-0.3.1.dist-info/WHEEL
hue_py-0.3.1.dist-info/top_level.txt
hue_py-0.3.1.dist-info/RECORD
