Metadata-Version: 2.1
Name: hue-py
Version: 0.3.1
Summary: Python client for Philips Hue bulbs
Home-page: https://github.com/mattboran/hue_py
Author: Matt Boran
Author-email: mattboran@gmail.com
License: UNKNOWN
Download-URL: https://github.com/mattboran/hue_py/releases/download/0.3.1/hue_py-0.3.1-py3-none-any.whl
Platform: UNKNOWN
Classifier: Development Status :: 3 - Alpha
Classifier: Programming Language :: Python :: 3
Classifier: License :: OSI Approved :: MIT License
Requires-Python: >3.6.0
Requires-Dist: requests (>=2.23.0)
Requires-Dist: webcolors (>=1.11)
Provides-Extra: test
Requires-Dist: pytest ; extra == 'test'
Requires-Dist: pytest-cov ; extra == 'test'
